em-0.3.dist-info/METADATA
em-0.3.dist-info/WHEEL
em-0.3.dist-info/RECORD
em-0.3.dist-info/pydist.json
em-0.3.dist-info/entry_points.txt
em-0.3.dist-info/top_level.txt
em-0.3.dist-info/DESCRIPTION.rst
em-0.3.data/scripts/em
em/__init__.py
em/locale/em.pot
em/locale/ru/LC_MESSAGES/em.mo
em/locale/uk/LC_MESSAGES/em.mo
