Metadata-Version: 2.0
Name: em
Version: 0.3
Summary: Highlight some PATTERN in terminal's STDOUT
Home-page: https://github.com/ikalnitsky/em
Author: Igor Kalnitsky
Author-email: igor@kalnitsky.org
License: BSD
Platform: Linux
Platform: MacOS
Platform: Unix
Classifier: Topic :: Utilities
Classifier: Environment :: Console
Classifier: Programming Language :: Python
Classifier: Programming Language :: Python :: 2
Classifier: Programming Language :: Python :: 2.7
Classifier: Programming Language :: Python :: 3
Classifier: Programming Language :: Python :: 3.2
Classifier: Programming Language :: Python :: 3.3
Classifier: Programming Language :: Python :: 3.4
Classifier: License :: OSI Approved :: BSD License
